<annotation>
	<folder></folder>
	<filename>burst_augment_22_blur315_jpg.rf.370110066487f10f2b7a07e99a08ebb2.jpg</filename>
	<path>burst_augment_22_blur315_jpg.rf.370110066487f10f2b7a07e99a08ebb2.jpg</path>
	<source>
		<database>roboflow.ai</database>
	</source>
	<size>
		<width>416</width>
		<height>416</height>
		<depth>3</depth>
	</size>
	<segmented>0</segmented>
	<object>
		<name>burst</name>
		<pose>Unspecified</pose>
		<truncated>0</truncated>
		<difficult>0</difficult>
		<occluded>0</occluded>
		<bndbox>
			<xmin>247</xmin>
			<xmax>323</xmax>
			<ymin>104</ymin>
			<ymax>229</ymax>
		</bndbox>
	</object>
	<object>
		<name>burst</name>
		<pose>Unspecified</pose>
		<truncated>0</truncated>
		<difficult>0</difficult>
		<occluded>0</occluded>
		<bndbox>
			<xmin>67</xmin>
			<xmax>216</xmax>
			<ymin>103</ymin>
			<ymax>310</ymax>
		</bndbox>
	</object>
</annotation>
